jobspire_nitra/__init__.py
jobspire_nitra/main.py
jobspire_nitra-0.1.9.dist-info/LICENSE
jobspire_nitra-0.1.9.dist-info/METADATA
jobspire_nitra-0.1.9.dist-info/WHEEL
jobspire_nitra-0.1.9.dist-info/top_level.txt
jobspire_nitra-0.1.9.dist-info/RECORD
