Metadata-Version: 2.1
Name: jobspire-nitra
Version: 0.1.9
Summary: Nitra
Home-page: https://github.com/HBS-Economics/nitra.git
Author: JobSpire team
Author-email: <info@jobspire.com>
Keywords: python,nitra package
Requires-Python: >=3.8
License-File: LICENSE
Requires-Dist: requests
